README.md
setup.py
async_request/__init__.py
async_request/crawler.py
async_request/fetcher.py
async_request/request.py
async_request/response.py
async_request/spider.py
async_request/utils.py
async_request.egg-info/PKG-INFO
async_request.egg-info/SOURCES.txt
async_request.egg-info/dependency_links.txt
async_request.egg-info/requires.txt
async_request.egg-info/top_level.txt
test/__init__.py
test/spider.py