Metadata-Version: 2.1
Name: async-request
Version: 0.1888
Summary: A lightweight network request framework
Home-page: https://github.com/financialfly/async-request
Author: financial
Author-email: 1012593988@qq.com
Maintainer: financial
Maintainer-email: 1012593988@qq.com
License: BSD License
Platform: all
Classifier: Development Status :: 4 - Beta
Classifier: Operating System :: OS Independent
Classifier: Intended Audience :: Developers
Classifier: License :: OSI Approved :: BSD License
Classifier: Programming Language :: Python
Classifier: Programming Language :: Python :: Implementation
Classifier: Programming Language :: Python :: 3.7
Classifier: Topic :: Software Development :: Libraries
